openBOS_GPU/__init__.py
openBOS_GPU/culculate_refractiveindex.py
openBOS_GPU/reconstruction.py
openBOS_GPU/reconstruction_utils.py
openBOS_GPU/utils.py
openBOS_GPU-0.0.6.dist-info/LICENSE
openBOS_GPU-0.0.6.dist-info/METADATA
openBOS_GPU-0.0.6.dist-info/WHEEL
openBOS_GPU-0.0.6.dist-info/top_level.txt
openBOS_GPU-0.0.6.dist-info/RECORD
