Metadata-Version: 2.1
Name: openBOS-GPU
Version: 0.0.6
Summary: the library of Background Oriented Schlieren
Home-page: https://github.com/ogayuuki0202/openBOS-GPU
Download-URL: https://github.com/ogayuuki0202/openBOS-GPU
Author: Yuuki Ogasawara
Author-email: yukiogasawara.research@gmail.com
Maintainer: Yuuki Ogasawara
Maintainer-email: yukiogasawara.research@gmail.com
License: GNU GENERAL PUBLIC LICENSE,
Classifier: Intended Audience :: Science/Research
Classifier: License :: OSI Approved :: GNU Lesser General Public License v3 (LGPLv3)
Classifier: Programming Language :: Python :: 3
Classifier: Programming Language :: Python :: 3.6
Classifier: Programming Language :: Python :: 3.7
Classifier: Programming Language :: Python :: 3.8
Classifier: Programming Language :: Python :: 3.9
Classifier: Programming Language :: Python :: 3 :: Only
Classifier: Topic :: Scientific/Engineering
Classifier: Topic :: Scientific/Engineering :: Visualization
Classifier: Topic :: Multimedia :: Graphics
Classifier: Framework :: Matplotlib
Requires-Python: >=3.6
License-File: LICENSE
Requires-Dist: numpy<2.0,>=1.20.3
Requires-Dist: tqdm>=4.0
